ten_vad/__init__.py
ten_vad/lib/Linux/x64/libten_vad.so
ten_vad/lib/Windows/x64/ten_vad.dll
ten_vad/lib/Windows/x86/ten_vad.dll
ten_vad/lib/macOS/ten_vad.framework/Versions/A/ten_vad
ten_vad-1.0.6.8.dist-info/licenses/LICENSE
ten_vad-1.0.6.8.dist-info/licenses/NOTICES
ten_vad-1.0.6.8.dist-info/METADATA
ten_vad-1.0.6.8.dist-info/WHEEL
ten_vad-1.0.6.8.dist-info/top_level.txt
ten_vad-1.0.6.8.dist-info/RECORD
