Metadata-Version: 2.4
Name: ten_vad
Version: 1.0.6.8
Summary: Voice Activity Detector (VAD) : low-latency, high-performance and lightweight
License-File: LICENSE
License-File: NOTICES
Dynamic: description
Dynamic: description-content-type
Dynamic: license-file
Dynamic: summary
